{
  "plant_name": "சிருமலை வாழை",
  "common_names_val": "சிறுமலை வாழை, மலை வாழை, சிறு வாழை",
  "local_name_val": "சிறுமலை வாழை (தமிழ்)",
  "family_val": "முசேசியே",
  "origin_val": "சிறுமலை மலைகள், திண்டுக்கல், தமிழ்நாடு, இந்தியா",
  "plant_type_val": "வற்றாத மூலிகையான மோனோகோட்",
  "variety_val": "சிறுமலை - சிறிய, இனிமையான மலை வகை; தமிழ்நாட்டில் இருந்து ஜி.ஐ",
  "avg_lifespan_val": "உறிஞ்சிகள் வழியாக வற்றாதது; தனிப்பட்ட ஆலை 18-24 மாதங்கள்",
  "growth_habit_val": "சூடோஸ்டெம் கொண்ட மூலிகை செடியை ஒட்டுதல்; பெரும்பாலான வகைகளை விட சிறியது",
  "plant_size_val": "1.5-2.5 மீட்டர் உயரம்; சிறிய வகை",
  "leaves_val": "பெரிய, நீள்வட்ட, பிரகாசமான பச்சை; 1.5-2 மீட்டர் நீளம்",
  "fruit_val": "சிறியது, 8-12 செ.மீ.; மெல்லிய தோல்; மிகவும் இனிமையான, நறுமண சதை",
  "fruit_color_val": "பழுத்தவுடன் மஞ்சள்; மெல்லிய தலாம்",
  "root_system_val": "நார்ச்சத்து, ஆழமற்றது; நிலத்தடி வேர்த்தண்டுக்கிழங்கு வழியாக பரவுகிறது",
  "climate_val": "வெப்பமண்டலம்; 600-1200 மீ உயரமுள்ள மலை நிலைகளில் வளர்கிறது",
  "temp_range_val": "20-30 டிகிரி செல்சியஸ்; குளிர்ந்த மலை வெப்பநிலையை பொறுத்துக்கொள்கிறது",
  "rainfall_val": "ஆண்டுதோறும் 1200-2500 மி.மீ",
  "soil_type_val": "கரிமப் பொருட்கள் நிறைந்த நன்கு வடிகட்டிய களிமண் மண்",
  "soil_ph_val": "6.0–7.5",
  "sun_req_val": "முழு சூரியன் முதல் பகுதி நிழல் வரை",
  "spacing_val": "தாவரங்களுக்கு இடையில் 2-3 மீட்டர்",
  "water_req_val": "மிதமானது முதல் உயர்ந்தது; நிலையான ஈரப்பதம் தேவை",
  "can_pots_val": "ஆம், பெரிய கொள்கலன்களில் (50+ லிட்டர்)",
  "fert_schedule_val": "மாதாந்திர; பழத்தின் தரத்திற்கு பொட்டாசியம் நிறைந்த உரம்",
  "organic_fert_val": "தொழு உரம், மண்புழு உரம், மர சாம்பல், வேப்பம் பிண்ணாக்கு",
  "common_pests_val": "வாழை அந்துப்பூச்சி, அசுவினி, த்ரிப்ஸ்",
  "common_diseases_val": "பனாமா வாடல், சிகடோகா இலைப்புள்ளி, கொத்து மேல் வைரஸ்",
  "flowering_months_val": "நடவு செய்த 10-14 மாதங்கள்",
  "days_harvest_val": "பூக்கும் 90-120 நாட்களுக்குப் பிறகு",
  "avg_yield_val": "ஒரு கொத்து 8-15 கிலோ",
  "poll_type_val": "பார்த்தீனோகார்பிக்; மகரந்த சேர்க்கை தேவையில்லை",
  "prop_cuttings_val": "வாள் உறிஞ்சுபவர்களுக்கு முன்னுரிமை; திசு வளர்ப்பும் கிடைக்கிறது",
  "commercial_val": "சிறுமலை மலை, திண்டுக்கல் மாவட்டம், தமிழ்நாடு",
  "market_uses_val": "பிரீமியம் புதிய பழங்கள்; GI-குறியிடப்பட்ட தயாரிப்பு அதிக விலையைக் கட்டளையிடுகிறது",
  "market_value_val": "ஒரு டசனுக்கு ₹60–120; வழக்கமான வாழைப்பழங்களை விட பிரீமியம்",
  "calories_val": "100 கிராமுக்கு 89 கிலோகலோரி",
  "fiber_val": "100 கிராமுக்கு 2.6 கிராம்",
  "potassium_val": "100 கிராமுக்கு 358 மி.கி",
  "vitc_val": "100 கிராமுக்கு 8.7 மி.கி"
}